telicent_labels/__init__.py
telicent_labels/idh_model.py
telicent_labels/security_labels.py
telicent_labels/telicent_model.py
telicent_labels/telicentv1.py
telicent_labels/telicentv2.py
telicent_label_builder-0.1.7.dist-info/LICENSE
telicent_label_builder-0.1.7.dist-info/LICENSE.md
telicent_label_builder-0.1.7.dist-info/METADATA
telicent_label_builder-0.1.7.dist-info/NOTICE
telicent_label_builder-0.1.7.dist-info/WHEEL
telicent_label_builder-0.1.7.dist-info/top_level.txt
telicent_label_builder-0.1.7.dist-info/RECORD
