Metadata-Version: 2.1
Name: telicent-label-builder
Version: 0.1.7
Summary: A helper package for creating and building security labels for telicent-lib
Author-email: Telicent Ltd <opensource@telicent.io>
License: Apache License
Project-URL: Repository, https://github.com/telicent-oss/label-builder
Project-URL: Changelog, https://github.com/telicent-oss/label-builder/blob/main/CHANGELOG.md
Classifier: Development Status :: 3 - Alpha
Classifier: Programming Language :: Python :: 3.10
Classifier: Programming Language :: Python :: 3.11
Classifier: Programming Language :: Python :: 3.12
Classifier: Programming Language :: Python :: 3.13
Classifier: Programming Language :: Python :: 3 :: Only
Classifier: Topic :: Software Development
Classifier: Typing :: Typed
Classifier: Operating System :: Microsoft :: Windows
Classifier: Operating System :: POSIX
Classifier: Operating System :: Unix
Classifier: Operating System :: MacOS
Requires-Python: >=3.10
License-File: LICENSE
License-File: LICENSE.md
License-File: NOTICE
Requires-Dist: pydantic
Provides-Extra: dev
Requires-Dist: pre-commit ==3.7.0 ; extra == 'dev'
Requires-Dist: ruff ==0.4.2 ; extra == 'dev'
Requires-Dist: mypy ==1.10.0 ; extra == 'dev'
